{"SubTexture":[{"width":" 172","y":" 172","height":" 132","name":"bz01","x":" 829"},{"rotated":"true","y":" 11","width":" 235","height":" 136","name":"bz02","x":" 239"},{"rotated":"true","y":" 255","width":" 298","height":" 160","name":"bz03","x":" 420"},{"rotated":"true","y":" 242","width":" 311","height":" 189","name":"bz04","x":" 2"},{"width":" 296","y":" 37","height":" 209","name":"bz05","x":" 377"},{"rotated":"true","y":" 248","width":" 305","height":" 225","name":"bz06","x":" 193"},{"rotated":"true","y":" 273","width":" 280","height":" 245","name":"bz07","x":" 582"},{"width":" 235","y":" 3","height":" 237","name":"bz08","x":" 2"},{"width":" 102","y":" 30","height":" 112","name":"bz09","x":" 798"},{"width":" 89","y":" 13","height":" 22","name":"dy","x":" 460"},{"width":" 142","y":" 144","height":" 127","name":"xy","x":" 675"},{"width":" 36","y":" 2","height":" 33","name":"zbsl01","x":" 377"},{"width":" 39","y":" 122","height":" 48","name":"zbsl02","x":" 962"},{"width":" 58","y":" 125","height":" 45","name":"zbsl03","x":" 902"},{"rotated":"true","y":" 306","width":" 247","height":" 175","name":"zbsl04","x":" 829"},{"rotated":"true","y":" 2","width":" 140","height":" 121","name":"zbsl05","x":" 675"},{"width":" 36","y":" 85","height":" 35","name":"zbsl06","x":" 950"},{"rotated":"true","y":" 3","width":" 32","height":" 43","name":"zbsl07","x":" 415"},{"width":" 46","y":" 84","height":" 39","name":"zbsl08","x":" 902"}],"imagePath":"zibaoshalu.png"}